copyright_claim/__init__.py
copyright_claim/copyright_claim.py
copyright_claim/dummy_copyright_claim.txt
copyright_claim-0.0.5.dist-info/METADATA
copyright_claim-0.0.5.dist-info/WHEEL
copyright_claim-0.0.5.dist-info/entry_points.txt
copyright_claim-0.0.5.dist-info/RECORD
