Metadata-Version: 2.1
Name: copyright-claim
Version: 0.0.5
Summary: Adds and removes copyright claims at the beginning of text files.
License: BSD-2-Clause License
Author: Gaël Cousin
Author-email: gcousin333@gmail.com
Requires-Python: >=3.7,<4.0
Classifier: License :: Other/Proprietary License
Classifier: Programming Language :: Python :: 3
Classifier: Programming Language :: Python :: 3.7
Classifier: Programming Language :: Python :: 3.8
Classifier: Programming Language :: Python :: 3.9
Classifier: Programming Language :: Python :: 3.10
Classifier: Programming Language :: Python :: 3.11
